mat_enm/ENMClient.py
mat_enm/__init__.py
mat_enm/enmscripting/__init__.py
mat_enm/enmscripting/__version__.py
mat_enm/enmscripting/enmscripting.py
mat_enm/enmscripting/enmsession.py
mat_enm/enmscripting/exceptions.py
mat_enm/enmscripting/command/__init__.py
mat_enm/enmscripting/command/command.py
mat_enm/enmscripting/common/__init__.py
mat_enm/enmscripting/common/element.py
mat_enm/enmscripting/common/file.py
mat_enm/enmscripting/common/output.py
mat_enm/enmscripting/private/__init__.py
mat_enm/enmscripting/private/executionhandler.py
mat_enm/enmscripting/private/logging_util.py
mat_enm/enmscripting/private/overrides.py
mat_enm/enmscripting/private/poller.py
mat_enm/enmscripting/private/retry.py
mat_enm/enmscripting/private/session.py
mat_enm/enmscripting/security/__init__.py
mat_enm/enmscripting/security/authenticator.py
mat_enm/enmscripting/terminal/__init__.py
mat_enm/enmscripting/terminal/terminal.py
mat_enm/enmscripting/test/__init__.py
mat_enm/enmscripting/test/element_iterator.py
mat_enm/enmscripting/test/json_generator.py
mat_enm/enmscripting/test/session_mock_utils.py
mat_enm/enmscripting/test/test_command.py
mat_enm/enmscripting/test/test_command_get_output.py
mat_enm/enmscripting/test/test_element.py
mat_enm/enmscripting/test/test_enmsession.py
mat_enm/enmscripting/test/test_executor.py
mat_enm/enmscripting/test/test_executor_get_url.py
mat_enm/enmscripting/test/test_open_external_session.py
mat_enm/enmscripting/test/test_open_internal_session.py
mat_enm/enmscripting/test/test_output.py
mat_enm/enmscripting/test/test_poller.py
mat_enm/enmscripting/test/test_result_groups_stress.py
mat_enm/enmscripting/test/test_retry.py
mat_enm/enmscripting/test/test_session.py
mat_enm/enmscripting/test/test_terminal.py
mat_enm/utils/cm_command_type.py
mat_enm/utils/constants.py
mat_enm/utils/error_code.py
mat_enm-0.0.13.dist-info/METADATA
mat_enm-0.0.13.dist-info/WHEEL
mat_enm-0.0.13.dist-info/licenses/LICENSE
mat_enm-0.0.13.dist-info/RECORD
