Metadata-Version: 2.1
Name: mat_enm
Version: 0.0.13
Summary: https://gitlab.com/lucas.larroque/mat-lib/-/blob/main/mat_enm/README.md
Project-URL: Homepage, https://gitlab.com/lucas.larroque/mat-lib/-/blob/main/mat_enm
Project-URL: Bug Tracker, https://gitlab.com/lucas.larroque/mat-lib/-/issues
Author-email: lucas <lucas.larroque@iquall.net>
License: MIT License
License-File: LICENSE
Classifier: License :: OSI Approved :: MIT License
Classifier: Operating System :: OS Independent
Classifier: Programming Language :: Python :: 3
Requires-Python: >=3.8
